{
  "project_info": {
    "project_number": "439091548426",
    "firebase_url": "https://myflutterapp-6481b-default-rtdb.firebaseio.com",
    "project_id": "myflutterapp-6481b",
    "storage_bucket": "myflutterapp-6481b.appspot.com"
  },
  "client": [
    {
      "client_info": {
        "mobilesdk_app_id": "1:439091548426:android:7d093ed7ea900674c86af3",
        "android_client_info": {
          "package_name": "com.example.todo_list"
        }
      },
      "oauth_client": [
        {
          "client_id": "439091548426-sarkekef53gthhff5c89qrukm99jp3u6.apps.googleusercontent.com",
          "client_type": 3
        }
      ],
      "api_key": [
        {
          "current_key": "AIzaSyCtnvjrotZAEyfQxhH9sl2aU_txwWX8ZrU"
        }
      ],
      "services": {
        "appinvite_service": {
          "other_platform_oauth_client": [
            {
              "client_id": "439091548426-sarkekef53gthhff5c89qrukm99jp3u6.apps.googleusercontent.com",
              "client_type": 3
            }
          ]
        }
      }
    }
  ],
  "configuration_version": "1"
}